{
  "type": "page",
  "body": [
    {
      "type": "crud",
      "id": "u:ab98d3213d61",
      "api": "get: --server--/admin/manage/menu/list",
      "syncLocation": false,
      "autoGenerateFilter": true,
      "filter": {
        "debug": false,
        "title": "条件搜索",
        "body": [
          {
            "type": "group",
            "body": [
              {
                "type": "input-text",
                "name": "app",
                "label": "应用英文名",
                "clearable": true,
                "trimContents": true,
                "size": "sm",
                "id": "u:0d0c55ded360"
              },
              {
                "type": "input-text",
                "name": "label",
                "label": "菜单名称",
                "clearable": true,
                "trimContents": true,
                "size": "sm",
                "id": "u:eb72c3488567"
              },
              {
                "type": "input-text",
                "name": "pid",
                "label": "父菜单ID",
                "clearable": true,
                "trimContents": true,
                "size": "sm",
                "id": "u:4a3f4268e6a0",
                "value": -1
              }
            ],
            "id": "u:be0cb0396208"
          }
        ],
        "actions": [
          {
            "type": "submit",
            "level": "primary",
            "label": "查询",
            "id": "u:8a987dea7051"
          },
          {
            "type": "reset",
            "label": "重置",
            "id": "u:c0fd4db15840"
          }
        ],
        "id": "u:76871bf4b594",
        "feat": "Insert",
        "labelAlign": "left"
      },
      "filterTogglable": true,
      "headerToolbar": [
        "filter-toggler",
        {
          "type": "button",
          "label": "创建",
          "level": "primary",
          "actionType": "dialog",
          "className": "left",
          "dialog": {
            "title": "创建指定应用中的一级菜单",
            "size": "full",
            "closeOnEsc": true,
            "closeOnOutside": true,
            "body": {
              "type": "form",
              "api": "post: --server--/admin/manage/menu/save",
              "body": [
                {
                  "name": "app",
                  "type": "input-text",
                  "label": "应用英文名",
                  "required": true
                },
                {
                  "name": "label",
                  "type": "input-text",
                  "label": "菜单名称",
                  "required": true
                },
                {
                  "name": "icon",
                  "type": "input-text",
                  "label": "菜单图标",
                  "value": "fa fa-cube"
                },
                {
                  "type": "input-text",
                  "name": "url",
                  "label": "菜单url"
                },
                {
                  "name": "page_key",
                  "type": "input-text",
                  "label": "低代码page_key"
                },
                {
                  "name": "pid",
                  "type": "input-text",
                  "label": "父菜单id",
                  "visible": false,
                  "value": -1
                },
                {
                  "name": "rule_key",
                  "type": "input-text",
                  "label": "rule_key 权限标识"
                },
                {
                  "name": "visible",
                  "type": "input-text",
                  "label": "菜单可见性",
                  "value": true
                },
                {
                  "name": "redirect",
                  "type": "input-text",
                  "label": "重定向链接"
                }
              ]
            }
          },
          "id": "u:e726ddbac670"
        },
        {
          "type": "columns-toggler",
          "align": "right"
        },
        {
          "type": "drag-toggler",
          "align": "right"
        },
        {
          "type": "pagination",
          "align": "right"
        }
      ],
      "columns": [
        {
          "name": "id",
          "type": "text",
          "label": "id",
          "id": "u:579e98287134"
        },
        {
          "name": "app",
          "type": "text",
          "label": "应用英文名",
          "valueField": "value",
          "labelField": "label",
          "id": "u:5a15a75112be",
          "placeholder": "-"
        },
        {
          "name": "label",
          "type": "text",
          "label": "菜单名称",
          "valueField": "value",
          "labelField": "label",
          "id": "u:2c1f0f45c164",
          "placeholder": "-"
        },
        {
          "name": "icon",
          "type": "text",
          "label": "菜单图标",
          "id": "u:6a2aa03f819b",
          "placeholder": "-"
        },
        {
          "name": "pid",
          "type": "text",
          "label": "父菜单id",
          "id": "u:d820f634c3b7",
          "placeholder": "-"
        },
        {
          "name": "url",
          "type": "text",
          "label": "菜单url",
          "id": "u:2929eb142a8c",
          "placeholder": "-"
        },
        {
          "type": "text",
          "label": "菜单page_key",
          "id": "u:7b999c5e43ea",
          "placeholder": "-",
          "name": "page_key"
        },
        {
          "name": "rule_key",
          "type": "text",
          "label": "菜单rule_key",
          "id": "u:6986a85c487c",
          "placeholder": "-"
        },
        {
          "name": "visible",
          "type": "text",
          "label": "菜单可见性",
          "id": "u:0b01622c4085",
          "placeholder": "-"
        },
        {
          "name": "redirect",
          "type": "text",
          "label": "重定向链接",
          "id": "u:484b25dcc3c6",
          "placeholder": "-"
        },
        {
          "type": "operation",
          "label": "操作",
          "buttons": [
            {
              "type": "button",
              "label": "编辑",
              "level": "primary",
              "actionType": "dialog",
              "dialog": {
                "title": "编辑app信息",
                "size": "full",
                "closeOnEsc": true,
                "closeOnOutside": true,
                "body": {
                  "api": "post: --server--/admin/manage/menu/save",
                  "body": [
                    {
                      "name": "id",
                      "type": "hidden",
                      "label": "id",
                      "required": true
                    },
                    {
                      "name": "app",
                      "type": "input-text",
                      "label": "应用英文名"
                    },
                    {
                      "name": "label",
                      "type": "input-text",
                      "label": "菜单名称"
                    },
                    {
                      "name": "icon",
                      "type": "input-text",
                      "label": "菜单图标"
                    },
                    {
                      "name": "url",
                      "type": "input-text",
                      "label": "菜单url"
                    },
                    {
                      "type": "input-text",
                      "name": "page_key",
                      "label": "低代码page_key"
                    },
                    {
                      "name": "pid",
                      "type": "input-text",
                      "label": "父菜单id"
                    },
                    {
                      "name": "rule_key",
                      "type": "input-text",
                      "label": "rule_key 权限标识"
                    },
                    {
                      "name": "visible",
                      "type": "input-text",
                      "label": "菜单可见性"
                    },
                    {
                      "name": "redirect",
                      "type": "input-text",
                      "label": "重定向链接"
                    }
                  ],
                  "type": "form"
                }
              },
              "id": "u:980b48b80de5"
            },
            {
              "type": "button",
              "label": "创建子菜单",
              "level": "success",
              "actionType": "dialog",
              "dialog": {
                "title": "子菜单信息",
                "size": "full",
                "closeOnEsc": true,
                "closeOnOutside": true,
                "body": {
                  "api": "post: --server--/admin/manage/menu/save",
                  "body": [
                    {
                      "name": "app",
                      "type": "input-text",
                      "label": "应用英文名",
                      "required": true
                    },
                    {
                      "name": "label",
                      "type": "input-text",
                      "label": "菜单名称",
                      "required": true
                    },
                    {
                      "name": "icon",
                      "type": "input-text",
                      "label": "菜单图标"
                    },
                    {
                      "name": "url",
                      "type": "input-text",
                      "label": "菜单url",
                      "required": true
                    },
                    {
                      "type": "input-text",
                      "name": "page_key",
                      "label": "低代码page_key",
                      "required": true
                    },
                    {
                      "name": "pid",
                      "type": "input-text",
                      "label": "父菜单id",
                      "value": "${id}"
                    },
                    {
                      "name": "rule_key",
                      "type": "input-text",
                      "label": "rule_key 权限标识",
                      "value": "rule_key"
                    },
                    {
                      "name": "visible",
                      "type": "input-text",
                      "label": "菜单可见性",
                      "value": true
                    },
                    {
                      "name": "redirect",
                      "type": "input-text",
                      "label": "重定向链接"
                    }
                  ],
                  "type": "form"
                }
              },
              "id": "u:446e9ff7dab1",
              "visibleOn": "pid==-1"
            },
            {
              "type": "button",
              "label": "查看子菜单",
              "level": "info",
              "actionType": "ajax",
              "id": "u:dfcd0adeda62",
              "visibleOn": "pid==-1",
              "api": "get: --server--/admin/manage/menu/list?app=${app}&pid=${id}",
              "redirect": "../menu"
            }
          ],
          "id": "u:e869b96178f3",
          "placeholder": "-"
        }
      ],
      "perPageAvailable": [
        5,
        10,
        20,
        50,
        100
      ],
      "messages": {}
    }
  ],
  "id": "u:fb1c598358be",
  "asideResizor": false,
  "pullRefresh": {
    "disabled": true
  }
}